gruzau/__init__.py
gruzau/dump.py
gruzau/grep.py
gruzau/load.py
gruzau/speak.py
gruzau-0.3.dist-info/COPYING
gruzau-0.3.dist-info/METADATA
gruzau-0.3.dist-info/WHEEL
gruzau-0.3.dist-info/entry_points.txt
gruzau-0.3.dist-info/top_level.txt
gruzau-0.3.dist-info/RECORD
