Metadata-Version: 2.1
Name: gruzau
Version: 0.3
Summary: Plugins for uzoenr
Author: sherekhan
Classifier: Development Status :: 1 - Planning
Classifier: Environment :: Console
Classifier: Intended Audience :: System Administrators
Classifier: License :: OSI Approved :: GNU General Public License v3 or later (GPLv3+)
Classifier: Operating System :: OS Independent
Classifier: Programming Language :: Python :: 3 :: Only
Classifier: Topic :: Internet :: WWW/HTTP :: Browsers
Classifier: Topic :: Utilities
Classifier: Natural Language :: Russian
Requires-Python: >=3.6
License-File: COPYING
Requires-Dist: uzoenr (>=11)
